intelmo/__init__.py
intelmo/models/__init__.py
intelmo/models/article.py
intelmo/models/block.py
intelmo/models/composition.py
intelmo/models/form.py
intelmo/models/rss.py
intelmo/models/task.py
intelmo/server.py
intelmo/utils/__init__.py
intelmo/utils/extraction.py
intelmo/webui/__init__.py
intelmo/webui/header.py
intelmo/webui/reader_page.py
intelmo/webui/rss_page.py
intelmo-1.1.2.dist-info/LICENSE
intelmo-1.1.2.dist-info/METADATA
intelmo-1.1.2.dist-info/WHEEL
intelmo-1.1.2.dist-info/RECORD
