Metadata-Version: 2.1
Name: intelmo
Version: 1.1.2
Summary: 
Author: Chunxu Yang
Author-email: chunxuyang@ucla.edu
Requires-Python: >=3.9,<4.0
Classifier: Programming Language :: Python :: 3
Classifier: Programming Language :: Python :: 3.9
Classifier: Programming Language :: Python :: 3.10
Classifier: Programming Language :: Python :: 3.11
Requires-Dist: bigtree (>=0.12.3,<0.13.0)
Requires-Dist: feedparser (>=6.0.10,<7.0.0)
Requires-Dist: newspaper3k (>=0.2.8,<0.3.0)
Requires-Dist: nicegui (>=1.3.14,<2.0.0)
Requires-Dist: nltk (>=3.8.1,<4.0.0)
Requires-Dist: pydantic (>=2.3.0,<3.0.0)
